look4bas/__init__.py
look4bas/__main__.py
look4bas/_look4bas.py
look4bas/api.py
look4bas/cache.py
look4bas/ccrepo.py
look4bas/cli.py
look4bas/config.py
look4bas/database.py
look4bas/display.py
look4bas/elements.py
look4bas/emsl.py
look4bas/gaussian94.py
look4bas/main.py
look4bas/store.py
look4bas/test_functionality.py
look4bas/test_gaussian94.py
look4bas/tlsutil.py
look4bas/util.py
look4bas/basis_format/__init__.py
look4bas/basis_format/cfour.py
look4bas/basis_format/constants.py
look4bas/basis_format/gaussian94.py
look4bas/basis_format/nwchem.py
look4bas/basis_format/orca.py
look4bas/basis_format/pyscf.py
look4bas/basis_format/qchem.py
look4bas/basis_format/test_gaussian94.py
look4bas/basis_format/test_nwchem.py
look4bas/basis_format/test_orca.py
look4bas/basis_format/test_pyscf.py
look4bas/basis_format/test_qchem.py
look4bas/basis_format/turbomole.py
look4bas-0.3.1.data/scripts/look4bas
look4bas-0.3.1.dist-info/LICENCE
look4bas-0.3.1.dist-info/LICENSE
look4bas-0.3.1.dist-info/METADATA
look4bas-0.3.1.dist-info/WHEEL
look4bas-0.3.1.dist-info/top_level.txt
look4bas-0.3.1.dist-info/RECORD
